checkpointer/__init__.py
checkpointer/checkpoint.py
checkpointer/fn_ident.py
checkpointer/fn_string.py
checkpointer/import_mappings.py
checkpointer/object_hash.py
checkpointer/print_checkpoint.py
checkpointer/types.py
checkpointer/utils.py
checkpointer/storages/__init__.py
checkpointer/storages/memory_storage.py
checkpointer/storages/pickle_storage.py
checkpointer/storages/storage.py
checkpointer-2.14.7.dist-info/METADATA
checkpointer-2.14.7.dist-info/WHEEL
checkpointer-2.14.7.dist-info/licenses/ATTRIBUTION.md
checkpointer-2.14.7.dist-info/licenses/LICENSE
checkpointer-2.14.7.dist-info/RECORD
