Metadata-Version: 2.4
Name: checkpointer
Version: 2.14.7
Summary: checkpointer adds code-aware caching to Python functions, maintaining correctness and speeding up execution as your code changes.
Project-URL: Repository, https://github.com/Reddan/checkpointer.git
Author: Hampus Hallman
License-Expression: MIT
License-File: ATTRIBUTION.md
License-File: LICENSE
Keywords: async,cache,caching,data analysis,data processing,fast,hashing,invalidation,memoization,optimization,performance,workflow
Classifier: Programming Language :: Python :: 3.11
Classifier: Programming Language :: Python :: 3.12
Classifier: Programming Language :: Python :: 3.13
Requires-Python: >=3.11
